stabilize/__init__.py
stabilize/assertions.py
stabilize/audit.py
stabilize/conditions.py
stabilize/errors.py
stabilize/launcher.py
stabilize/lifecycle.py
stabilize/logging.py
stabilize/metrics.py
stabilize/orchestrator.py
stabilize/py.typed
stabilize/recovery.py
stabilize/tracing.py
stabilize/verification.py
stabilize/cli/__init__.py
stabilize/cli/commands.py
stabilize/cli/config.py
stabilize/cli/main.py
stabilize/cli/migrations.py
stabilize/cli/prompt_text.py
stabilize/context/__init__.py
stabilize/context/stage_context.py
stabilize/dag/__init__.py
stabilize/dag/graph.py
stabilize/dag/topological.py
stabilize/handlers/__init__.py
stabilize/handlers/base.py
stabilize/handlers/cancel_stage.py
stabilize/handlers/complete_stage.py
stabilize/handlers/complete_task.py
stabilize/handlers/complete_workflow.py
stabilize/handlers/continue_parent_stage.py
stabilize/handlers/skip_stage.py
stabilize/handlers/start_stage.py
stabilize/handlers/start_task.py
stabilize/handlers/start_waiting_workflows.py
stabilize/handlers/start_workflow.py
stabilize/handlers/jump_to_stage/__init__.py
stabilize/handlers/jump_to_stage/handler.py
stabilize/handlers/jump_to_stage/reset.py
stabilize/handlers/jump_to_stage/traversal.py
stabilize/handlers/run_task/__init__.py
stabilize/handlers/run_task/error.py
stabilize/handlers/run_task/execution.py
stabilize/handlers/run_task/handler.py
stabilize/handlers/run_task/result.py
stabilize/handlers/run_task/verification.py
stabilize/migrations/__init__.py
stabilize/models/__init__.py
stabilize/models/stage.py
stabilize/models/status.py
stabilize/models/task.py
stabilize/models/workflow.py
stabilize/monitor/__init__.py
stabilize/monitor/data.py
stabilize/monitor/display/__init__.py
stabilize/monitor/display/constants.py
stabilize/monitor/display/fetcher.py
stabilize/monitor/display/interaction.py
stabilize/monitor/display/monitor.py
stabilize/monitor/display/rendering.py
stabilize/persistence/__init__.py
stabilize/persistence/connection.py
stabilize-0.15.4.dist-info/METADATA
stabilize-0.15.4.dist-info/WHEEL
stabilize-0.15.4.dist-info/entry_points.txt
stabilize-0.15.4.dist-info/licenses/LICENSE
stabilize-0.15.4.dist-info/RECORD
