Metadata-Version: 2.4
Name: stabilize
Version: 0.15.4
Summary: Highway Workflow Engine - Stabilize execution layer
Project-URL: Homepage, https://github.com/rodmena-limited/stabilize
Project-URL: Repository, https://github.com/rodmena-limited/stabilize
Project-URL: Issues, https://github.com/rodmena-limited/stabilize/issues
Author-email: Farshid Ashouri <farsheed.ashouri@gmail.com>
License: Apache-2.0
License-File: LICENSE
Keywords: dag,orchestration,pipeline,task-runner,workflow
Classifier: Development Status :: 4 - Beta
Classifier: Intended Audience :: Developers
Classifier: License :: OSI Approved :: Apache Software License
Classifier: Programming Language :: Python :: 3
Classifier: Programming Language :: Python :: 3.11
Classifier: Programming Language :: Python :: 3.12
Classifier: Programming Language :: Python :: 3.13
Classifier: Programming Language :: Python :: 3.14
Requires-Python: >=3.11
Requires-Dist: bulkman>=0.1.0
Requires-Dist: pydantic>=2.0
Requires-Dist: python-ulid>=2.0
Requires-Dist: resilient-circuit>=0.1.0
Provides-Extra: all
Requires-Dist: migretti>=0.3; extra == 'all'
Requires-Dist: opentelemetry-api>=1.20; extra == 'all'
Requires-Dist: opentelemetry-sdk>=1.20; extra == 'all'
Requires-Dist: psycopg[pool]>=3.0; extra == 'all'
Requires-Dist: structlog>=24.0; extra == 'all'
Provides-Extra: dev
Requires-Dist: migretti>=0.3; extra == 'dev'
Requires-Dist: mypy>=1.8; extra == 'dev'
Requires-Dist: opentelemetry-api>=1.20; extra == 'dev'
Requires-Dist: opentelemetry-sdk>=1.20; extra == 'dev'
Requires-Dist: psycopg[pool]>=3.0; extra == 'dev'
Requires-Dist: pytest-asyncio>=0.23; extra == 'dev'
Requires-Dist: pytest-xdist>=3.0; extra == 'dev'
Requires-Dist: pytest>=8.0; extra == 'dev'
Requires-Dist: ruff>=0.1; extra == 'dev'
Requires-Dist: structlog>=24.0; extra == 'dev'
Requires-Dist: testcontainers>=4.0; extra == 'dev'
Provides-Extra: observability
Requires-Dist: opentelemetry-api>=1.20; extra == 'observability'
Requires-Dist: opentelemetry-sdk>=1.20; extra == 'observability'
Requires-Dist: structlog>=24.0; extra == 'observability'
Provides-Extra: postgres
Requires-Dist: migretti>=0.3; extra == 'postgres'
Requires-Dist: psycopg[pool]>=3.0; extra == 'postgres'
